tactacai/__init__.py
tactacai/game.py
tactacai/interface.py
tactacai/statistics.py
tactacai-1.0.dist-info/LICENSE
tactacai-1.0.dist-info/METADATA
tactacai-1.0.dist-info/WHEEL
tactacai-1.0.dist-info/entry_points.txt
tactacai-1.0.dist-info/top_level.txt
tactacai-1.0.dist-info/RECORD
