Metadata-Version: 2.1
Name: tactacai
Version: 1.0
Summary: Tic Tac Toe game that allows you to play against a human or an AI powered by Minimax algorithm and also saves your score.
Home-page: https://github.com/vivekkdagar/TicTacAI
Author: Vivek Dagar
Author-email: vivekdagar2024@gmail.com
License: MIT License
License-File: LICENSE
Requires-Dist: prettytable ~=3.5.0
Requires-Dist: tabulate ~=0.9.0
Requires-Dist: click ~=8.1.7
Requires-Dist: setuptools ~=68.0.0
Requires-Dist: wheel
